gcloud_pyproxy/__init__.py
GCloudPyProxy-1.0b0.dist-info/LICENSE
GCloudPyProxy-1.0b0.dist-info/METADATA
GCloudPyProxy-1.0b0.dist-info/WHEEL
GCloudPyProxy-1.0b0.dist-info/top_level.txt
GCloudPyProxy-1.0b0.dist-info/RECORD
