Metadata-Version: 2.1
Name: GCloudPyProxy
Version: 1.0b0
Summary: This package provides proxy class for calling gcloud commands directly from Python.
Home-page: https://github.com/tomasvotava/gcloud-pyproxy
Author: Tomas Votava
Author-email: info@tomasvotava.eu
License: MIT License
Download-URL: https://github.com/tomasvotava/gcloud-pyproxy/archive/master.zip
Project-URL: Bug Tracker, https://github.com/tomasvotava/gcloud-pyproxy/issues
Project-URL: Documentation, https://github.com/tomasvotava/gcloud-pyproxy/blob/master/README.md
Project-URL: Source Code, https://github.com/tomasvotava/gcloud-pyproxy
Keywords: gcp google cloud platform gcloud python proxy
Platform: UNKNOWN
Classifier: License :: OSI Approved :: MIT License
Classifier: Programming Language :: Python :: 3
Classifier: Topic :: Software Development :: Build Tools
Classifier: Development Status :: 4 - Beta
